<?xml version="1.0"?>
<col:collection xmlns="http://cnx.rice.edu/collxml" xmlns:md="http://cnx.rice.edu/mdml" xmlns:col="http://cnx.rice.edu/collxml" xml:lang="en" type="Course" authors="Siyavula Uploaders">
  <metadata xmlns:md="http://cnx.rice.edu/mdml" mdml-version="0.5">
    <md:content-id>col11012</md:content-id>
    <md:title>Ekonomiese en Bestuurswetenskappe Graad 6</md:title>
    <md:license url="http://creativecommons.org/licenses/by/3.0/">Creative Commons Attribution License 3.0</md:license>
    <md:language>en</md:language>
    <md:uuid>deb0204b-078a-42ba-aa35-6e92c21aae57</md:uuid>
    <md:slug>ekonomiese-en-bestuurswetenskappe-graad-6</md:slug>
  </metadata>
  <col:content>
    <col:subcollection>
      <md:title>Kwartaal 1</md:title>
      <col:content>
        <col:module document="m24138"/>
        <col:module document="m24140"/>
        <col:module document="m24148"/>
      </col:content>
    </col:subcollection>
    <col:subcollection>
      <md:title>Kwartaal 2</md:title>
      <col:content>
        <col:module document="m24152"/>
        <col:module document="m24156"/>
        <col:module document="m24161"/>
      </col:content>
    </col:subcollection>
    <col:subcollection>
      <md:title>Kwartaal 3</md:title>
      <col:content>
        <col:module document="m24164"/>
        <col:module document="m24165"/>
        <col:module document="m24167"/>
        <col:module document="m24166"/>
      </col:content>
    </col:subcollection>
    <col:subcollection>
      <md:title>Kwartaal 4</md:title>
      <col:content>
        <col:module document="m24169"/>
      </col:content>
    </col:subcollection>
  </col:content>
</col:collection>
